kubelaunch/__init__.py
kubelaunch/cli.py
kubelaunch/commands/__init__.py
kubelaunch/commands/add_config.py
kubelaunch/commands/app.py
kubelaunch/commands/base.py
kubelaunch/commands/cluster.py
kubelaunch/commands/hello.py
kubelaunch/commands/init.py
kubelaunch/commands/apps/__init__.py
kubelaunch/commands/apps/jupyter.py
kubelaunch/commands/clusters/__init__.py
kubelaunch/commands/clusters/azure.py
kubelaunch/commands/clusters/gcp.py
kubelaunch-0.0.1.dist-info/DESCRIPTION.rst
kubelaunch-0.0.1.dist-info/METADATA
kubelaunch-0.0.1.dist-info/RECORD
kubelaunch-0.0.1.dist-info/WHEEL
kubelaunch-0.0.1.dist-info/entry_points.txt
kubelaunch-0.0.1.dist-info/metadata.json
kubelaunch-0.0.1.dist-info/top_level.txt
