Metadata-Version: 2.0
Name: kubelaunch
Version: 0.0.1
Summary: An opinionated AI stack built for Kubernetes by default
Home-page: https://github.com/kuberlytics/kubelaunch-cli
Author: Jason Kuruzovich
Author-email: jkuruzovich@gmail.com
License: UNKNOWN
Keywords: kubernetes analytics jupyterhub airflow
Platform: UNKNOWN
Classifier: Development Status :: 2 - Pre-Alpha
Classifier: License :: OSI Approved :: MIT License
Classifier: Natural Language :: English
Classifier: Programming Language :: Python :: 3.5
Classifier: Programming Language :: Python :: 3.6
Requires-Dist: docopt
Requires-Dist: ruamel.yaml
Provides-Extra: test
Requires-Dist: coverage; extra == 'test'
Requires-Dist: pytest; extra == 'test'
Requires-Dist: pytest-cov; extra == 'test'
